da_xn_island/__init__.py
da_xn_island/utils.py
da_xn_island-1.1.1.dist-info/LICENSE
da_xn_island-1.1.1.dist-info/METADATA
da_xn_island-1.1.1.dist-info/WHEEL
da_xn_island-1.1.1.dist-info/top_level.txt
da_xn_island-1.1.1.dist-info/RECORD
