Metadata-Version: 2.1
Name: da-xn-island
Version: 1.1.1
Summary: The Da-xn Island package allows you to get Da-xn Island API data instantly with simple functions!
Home-page: https://da-xn.com/packages
Author: Da-xn Software
Author-email: dan@da-xn.com
License: MIT
Keywords: da-xn.com,da-xn,da-xn island,api,windows,mac,linux
Platform: UNKNOWN
Classifier: Development Status :: 4 - Beta
Classifier: License :: OSI Approved :: MIT License
Classifier: Programming Language :: Python :: 3
Classifier: Programming Language :: Python :: 3.6
Classifier: Programming Language :: Python :: 3.7
Classifier: Programming Language :: Python :: 3.9
Classifier: Operating System :: OS Independent
Classifier: Intended Audience :: Developers
Classifier: Topic :: Software Development :: Libraries :: Python Modules
Requires-Python: >=3.6
Requires-Dist: requests
Requires-Dist: colorama
